DeepseekConversationEngine/__init__.py
DeepseekConversationEngine/deepseek_conversation_engine.py
DeepseekConversationEngine/deepseek_v3_tokenizer/tokenizer.json
DeepseekConversationEngine/deepseek_v3_tokenizer/tokenizer_config.json
DeepseekConversationEngine/提示库/专属猫娘.txt
DeepseekConversationEngine/提示库/可爱猫猫.txt
DeepseekConversationEngine/提示库/怼人模式.txt
DeepseekConversationEngine/提示库/编程教师.txt
DeepseekConversationEngine/提示库/翻译模式.txt
DeepseekConversationEngine/提示库/魅魔模式.txt
deepseekconversationengine-1.2.1.dist-info/licenses/LICENSE
deepseekconversationengine-1.2.1.dist-info/METADATA
deepseekconversationengine-1.2.1.dist-info/WHEEL
deepseekconversationengine-1.2.1.dist-info/top_level.txt
deepseekconversationengine-1.2.1.dist-info/RECORD
