Metadata-Version: 2.4
Name: DeepseekConversationEngine
Version: 1.2.1
Summary: 多人设、多场景、多论对话自动化管理
Home-page: https://github.com/yandifei/DeepseekConversationEngine
Author: 雁低飞
Author-email: 3058439878@qq.com
Classifier: Programming Language :: Python :: 3
Classifier: License :: OSI Approved :: MIT License
Classifier: Operating System :: Microsoft :: Windows :: Windows 11
Requires-Python: >=3.13.1
License-File: LICENSE
Requires-Dist: openai==1.79.0
Requires-Dist: Requests==2.32.3
Requires-Dist: setuptools==80.7.1
Requires-Dist: transformers==4.51.3
Dynamic: author
Dynamic: author-email
Dynamic: classifier
Dynamic: description
Dynamic: description-content-type
Dynamic: home-page
Dynamic: license-file
Dynamic: requires-dist
Dynamic: requires-python
Dynamic: summary
